mlrose_torch/__init__.py
mlrose_torch/activation.py
mlrose_torch/algorithms.py
mlrose_torch/decay.py
mlrose_torch/fitness.py
mlrose_torch/neural.py
mlrose_torch/opt_probs.py
mlrose_torch-0.1.0.dist-info/LICENSE
mlrose_torch-0.1.0.dist-info/METADATA
mlrose_torch-0.1.0.dist-info/WHEEL
mlrose_torch-0.1.0.dist-info/top_level.txt
mlrose_torch-0.1.0.dist-info/RECORD
