Metadata-Version: 2.1
Name: mlrose_torch
Version: 0.1.0
Summary: A highly optimized fork of 'MLROSe: Machine Learning, Randomized Optimization and Search', now with PyTorch and advanced NumPy vectorization.
Home-page: https://github.com/knakamura13/mlrose-torch
Author: Kyle Nakamura
License: BSD
Project-URL: Original Project, https://github.com/gkhayes/mlrose
Classifier: Intended Audience :: Education
Classifier: Intended Audience :: Science/Research
Classifier: Natural Language :: English
Classifier: License :: OSI Approved :: BSD License
Classifier: Programming Language :: Python
Classifier: Programming Language :: Python :: 3
Classifier: Programming Language :: Python :: 3.10
Classifier: Topic :: Scientific/Engineering
Classifier: Topic :: Scientific/Engineering :: Artificial Intelligence
Classifier: Topic :: Scientific/Engineering :: Mathematics
Classifier: Topic :: Software Development :: Libraries
Classifier: Topic :: Software Development :: Libraries :: Python Modules
Requires-Python: >=3.10
License-File: LICENSE
Requires-Dist: numpy
Requires-Dist: scipy
Requires-Dist: scikit-learn
Requires-Dist: six
Requires-Dist: torch
Requires-Dist: setuptools
